{"directed": false, "graph": {}, "nodes": [{"userID": "3112307444", "screen_name": "kimi_schneider", "id": "3112307444"}, {"userID": "573070026", "screen_name": "tanya_kroeze", "id": "573070026"}, {"userID": "837148062921326592", "screen_name": "ClementinaSele6", "id": "837148062921326592"}, {"userID": "836037619007934464", "screen_name": "LavetaPontarel3", "id": "836037619007934464"}, {"userID": "837525542500904964", "screen_name": "LucieJoynes2928", "id": "837525542500904964"}, {"userID": "836129686979633152", "screen_name": "CandiceGaillia6", "id": "836129686979633152"}, {"userID": "1259731788", "screen_name": "VictoriaHiscit", "id": "1259731788"}, {"userID": "3123130928", "screen_name": "ScwSchwartz", "id": "3123130928"}, {"userID": "836036342748340224", "screen_name": "hoylton_santa", "id": "836036342748340224"}, {"userID": "186462051", "screen_name": "ElisaMitchell_", "id": "186462051"}, {"userID": "836029174032687104", "screen_name": "TeshaAugeri2", "id": "836029174032687104"}, {"userID": "940179170", "screen_name": "Alycia_Linc", "id": "940179170"}, {"userID": "829532377814704128", "screen_name": "HermanBarken5", "id": "829532377814704128"}, {"userID": "836029214587408391", "screen_name": "TerenceGlenist3", "id": "836029214587408391"}, {"userID": "134287921", "screen_name": "thebluesnight", "id": "134287921"}, {"userID": "837500246057873409", "screen_name": "MarlanaGershon3", "id": "837500246057873409"}, {"userID": "836036781422215168", "screen_name": "ElenoreEverhar1", "id": "836036781422215168"}, {"userID": "236446188", "screen_name": "FredericaKiger", "id": "236446188"}, {"userID": "3153313781", "screen_name": "Paula_Jovanovic", "id": "3153313781"}, {"userID": "3427420774", "screen_name": "CarolineCervin", "id": "3427420774"}, {"userID": "834987809060478976", "screen_name": "dolcetto_gil", "id": "834987809060478976"}, {"userID": "830332229062516738", "screen_name": "LeighaDelara", "id": "830332229062516738"}, {"userID": "824116915652227077", "screen_name": "dalka_janetta", "id": "824116915652227077"}, {"userID": "3427561426", "screen_name": "Alexandra_Desga", "id": "3427561426"}, {"userID": "835398797643530240", "screen_name": "carello_leanne", "id": "835398797643530240"}, {"userID": "838566496024449024", "screen_name": "BaumiesterYaek1", "id": "838566496024449024"}, {"userID": "824118207917256704", "screen_name": "idell_clabough", "id": "824118207917256704"}, {"userID": "842028975606001665", "screen_name": "sandra_vsnv", "id": "842028975606001665"}, {"userID": "3147132222", "screen_name": "AngelinaGuerri", "id": "3147132222"}, {"userID": "838578962406096897", "screen_name": "CherilynCarlin5", "id": "838578962406096897"}, {"userID": "829517337678139392", "screen_name": "LuannaKohlmyer3", "id": "829517337678139392"}, {"userID": "218669263", "screen_name": "Caimbrieviena", "id": "218669263"}, {"userID": "944651106", "screen_name": "jimmie_chenee", "id": "944651106"}, {"userID": "945123446", "screen_name": "clyne_clinton", "id": "945123446"}, {"userID": "836429767805140993", "screen_name": "VaniaSposato1", "id": "836429767805140993"}], "links": [{"source": 8, "target": 27}], "multigraph": false}