{"directed": false, "graph": {}, "nodes": [{"userID": "732538705706094592", "screen_name": "Euro16fr", "id": "732538705706094592"}, {"userID": "3212109449", "screen_name": "sportsbetbf", "id": "3212109449"}, {"userID": "3304479251", "screen_name": "fbbbetf", "id": "3304479251"}, {"userID": "818852281953173506", "screen_name": "footymania247", "id": "818852281953173506"}, {"userID": "739474296670720000", "screen_name": "footballfbb", "id": "739474296670720000"}, {"userID": "3212799381", "screen_name": "snb188", "id": "3212799381"}, {"userID": "3197976827", "screen_name": "sporttlad", "id": "3197976827"}, {"userID": "3393922246", "screen_name": "oss365", "id": "3393922246"}, {"userID": "3049283884", "screen_name": "sportingnewsww", "id": "3049283884"}, {"userID": "4829436544", "screen_name": "sportsupdatefbb", "id": "4829436544"}, {"userID": "3198761433", "screen_name": "sntcor", "id": "3198761433"}, {"userID": "3233024092", "screen_name": "fbb888", "id": "3233024092"}, {"userID": "767756098216554500", "screen_name": "premlnb", "id": "767756098216554500"}, {"userID": "3298911327", "screen_name": "freebigbetsbs", "id": "3298911327"}, {"userID": "818835460147462144", "screen_name": "footynew247", "id": "818835460147462144"}, {"userID": "818823796773818368", "screen_name": "footballnew24", "id": "818823796773818368"}, {"userID": "3401089731", "screen_name": "dbofbb", "id": "3401089731"}, {"userID": "775345697361190912", "screen_name": "premnewuk", "id": "775345697361190912"}, {"userID": "3300234543", "screen_name": "freebigbetssky", "id": "3300234543"}, {"userID": "818847313116459008", "screen_name": "footynew24", "id": "818847313116459008"}, {"userID": "3213136127", "screen_name": "allsportsfbb", "id": "3213136127"}, {"userID": "3300897136", "screen_name": "roundclocksport", "id": "3300897136"}, {"userID": "3306921585", "screen_name": "fbbpp", "id": "3306921585"}, {"userID": "3046535075", "screen_name": "freebigbets", "id": "3046535075"}], "links": [{"source": 8, "target": 10}, {"source": 18, "target": 20}], "multigraph": false}