{"directed": false, "graph": {}, "nodes": [{"userID": "16348181", "screen_name": "theresaluff", "id": "16348181"}, {"userID": "2919025923", "screen_name": "courtneyk921", "id": "2919025923"}, {"userID": "3417697846", "screen_name": "ShinyHappyVicky", "id": "3417697846"}, {"userID": "2295954621", "screen_name": "OwlyKatz", "id": "2295954621"}, {"userID": "840662421484257280", "screen_name": "zoe_king_5987", "id": "840662421484257280"}, {"userID": "349060315", "screen_name": "TraceyHalpin", "id": "349060315"}, {"userID": "524276925", "screen_name": "robertf84230579", "id": "524276925"}, {"userID": "1292367463", "screen_name": "dresdondoll", "id": "1292367463"}, {"userID": "103907814", "screen_name": "aynslie70", "id": "103907814"}, {"userID": "975707834", "screen_name": "JANERAZZELL", "id": "975707834"}, {"userID": "814845351739924481", "screen_name": "ChloeGi73", "id": "814845351739924481"}, {"userID": "352658111", "screen_name": "raisingrosa", "id": "352658111"}, {"userID": "827557903779381249", "screen_name": "fibrofighter45", "id": "827557903779381249"}, {"userID": "4832946328", "screen_name": "mowatt_victoria", "id": "4832946328"}, {"userID": "14901445", "screen_name": "juliettdmills", "id": "14901445"}, {"userID": "377540403", "screen_name": "JackieTrow", "id": "377540403"}, {"userID": "478942479", "screen_name": "TheLynchyMob", "id": "478942479"}, {"userID": "1314693948", "screen_name": "jhill1105", "id": "1314693948"}, {"userID": "746346322660327424", "screen_name": "sunshinerooo", "id": "746346322660327424"}, {"userID": "822093179956641792", "screen_name": "freezingcoldrn", "id": "822093179956641792"}, {"userID": "843774682373509120", "screen_name": "Linnyloots", "id": "843774682373509120"}, {"userID": "2731743231", "screen_name": "zeezeefae", "id": "2731743231"}, {"userID": "99308126", "screen_name": "avstar25", "id": "99308126"}, {"userID": "441201769", "screen_name": "hibby84", "id": "441201769"}, {"userID": "797798171959316480", "screen_name": "elendouglas1", "id": "797798171959316480"}, {"userID": "714844008682536960", "screen_name": "zenakate1", "id": "714844008682536960"}, {"userID": "833404549117386752", "screen_name": "cattilltwit", "id": "833404549117386752"}, {"userID": "20844934", "screen_name": "SoozeHH", "id": "20844934"}, {"userID": "2341622478", "screen_name": "tobyjoshlucy", "id": "2341622478"}, {"userID": "46343866", "screen_name": "kittycatty12", "id": "46343866"}, {"userID": "2968745693", "screen_name": "samstone80", "id": "2968745693"}, {"userID": "24507327", "screen_name": "djaskew", "id": "24507327"}, {"userID": "2742681519", "screen_name": "sammysjb2", "id": "2742681519"}, {"userID": "41894658", "screen_name": "staceyhillx", "id": "41894658"}, {"userID": "29994495", "screen_name": "manonfirenow", "id": "29994495"}, {"userID": "787938140120047616", "screen_name": "DeeKazza", "id": "787938140120047616"}, {"userID": "394867363", "screen_name": "sassyamyfoster", "id": "394867363"}, {"userID": "469489270", "screen_name": "dianewhale1", "id": "469489270"}, {"userID": "716708370598731777", "screen_name": "LauraJayneTayl2", "id": "716708370598731777"}, {"userID": "288290247", "screen_name": "lfcvicki", "id": "288290247"}, {"userID": "1489867182", "screen_name": "QM2fan", "id": "1489867182"}, {"userID": "70679893", "screen_name": "SiBlunt", "id": "70679893"}, {"userID": "1484941760", "screen_name": "stanleystocks", "id": "1484941760"}, {"userID": "94772239", "screen_name": "RealGrosvenor", "id": "94772239"}, {"userID": "804301679894130689", "screen_name": "MatthewEccles4", "id": "804301679894130689"}, {"userID": "1580803902", "screen_name": "karenhi28186538", "id": "1580803902"}, {"userID": "49141637", "screen_name": "meech10", "id": "49141637"}, {"userID": "2724410978", "screen_name": "amyjf78", "id": "2724410978"}, {"userID": "804095143737511937", "screen_name": "wotawoman", "id": "804095143737511937"}, {"userID": "2744541100", "screen_name": "greendi321allen", "id": "2744541100"}, {"userID": "53329260", "screen_name": "cillastubbs", "id": "53329260"}, {"userID": "27000354", "screen_name": "gillbill1", "id": "27000354"}, {"userID": "140023036", "screen_name": "_JenniC_", "id": "140023036"}, {"userID": "240318233", "screen_name": "meisafairy", "id": "240318233"}, {"userID": "4869731938", "screen_name": "MerryHappy89", "id": "4869731938"}, {"userID": "158457913", "screen_name": "HELINAKIE", "id": "158457913"}, {"userID": "90701960", "screen_name": "dancer2712", "id": "90701960"}, {"userID": "51851392", "screen_name": "minilynn3", "id": "51851392"}, {"userID": "1494075139", "screen_name": "ComperJen", "id": "1494075139"}, {"userID": "827646397", "screen_name": "kloubear88", "id": "827646397"}, {"userID": "2942267333", "screen_name": "JamieLMDJs", "id": "2942267333"}, {"userID": "2284168970", "screen_name": "popikaoana", "id": "2284168970"}, {"userID": "2809979560", "screen_name": "9ehc2", "id": "2809979560"}, {"userID": "808292686562291712", "screen_name": "Firelover123", "id": "808292686562291712"}, {"userID": "80876513", "screen_name": "Beneaththegreen", "id": "80876513"}, {"userID": "21015191", "screen_name": "essexgirlSE", "id": "21015191"}, {"userID": "954414061", "screen_name": "SARAHGSMILE", "id": "954414061"}, {"userID": "2698729908", "screen_name": "sarelle777", "id": "2698729908"}, {"userID": "163061010", "screen_name": "operationboyler", "id": "163061010"}, {"userID": "746082238547304456", "screen_name": "laurawells82", "id": "746082238547304456"}, {"userID": "844654857181188096", "screen_name": "LollyJBerry", "id": "844654857181188096"}, {"userID": "320683324", "screen_name": "campbell_hayley", "id": "320683324"}, {"userID": "246216479", "screen_name": "x_itsonlyme_x", "id": "246216479"}, {"userID": "1614863684", "screen_name": "sandiewhittaker", "id": "1614863684"}, {"userID": "4924227454", "screen_name": "jessica_austin2", "id": "4924227454"}, {"userID": "2789019179", "screen_name": "amieO108", "id": "2789019179"}, {"userID": "1362766921", "screen_name": "DavuraLw", "id": "1362766921"}, {"userID": "4430460382", "screen_name": "eleanorar57", "id": "4430460382"}, {"userID": "988338996", "screen_name": "tinofpeas1892", "id": "988338996"}, {"userID": "543663086", "screen_name": "edoody2011", "id": "543663086"}, {"userID": "331036837", "screen_name": "JanetPalmer82", "id": "331036837"}, {"userID": "202400217", "screen_name": "ditchio1", "id": "202400217"}, {"userID": "14260458", "screen_name": "karlfoxley", "id": "14260458"}, {"userID": "808573669408653312", "screen_name": "MrsMcGowan59", "id": "808573669408653312"}, {"userID": "3491465248", "screen_name": "PeanutHog", "id": "3491465248"}, {"userID": "612315427", "screen_name": "Trulovesroo", "id": "612315427"}, {"userID": "1691985013", "screen_name": "RedChris74", "id": "1691985013"}, {"userID": "834679179652251648", "screen_name": "RoboneHayat", "id": "834679179652251648"}, {"userID": "380828101", "screen_name": "KateRoessler", "id": "380828101"}, {"userID": "2203746379", "screen_name": "wendymorecombe", "id": "2203746379"}, {"userID": "219981616", "screen_name": "PHILS4926", "id": "219981616"}, {"userID": "30863113", "screen_name": "ForLoveInLimbo", "id": "30863113"}, {"userID": "28799945", "screen_name": "Whittsmills", "id": "28799945"}, {"userID": "422458748", "screen_name": "kevchristy", "id": "422458748"}, {"userID": "285689796", "screen_name": "biancacranmer", "id": "285689796"}, {"userID": "4342371675", "screen_name": "GillianPalmer60", "id": "4342371675"}, {"userID": "196588526", "screen_name": "deanne2622", "id": "196588526"}, {"userID": "1575080857", "screen_name": "Chrisbobfletch", "id": "1575080857"}, {"userID": "3087143234", "screen_name": "SMckenzie166", "id": "3087143234"}, {"userID": "2225678060", "screen_name": "robbyprice55", "id": "2225678060"}, {"userID": "227323052", "screen_name": "wildabouttheboy", "id": "227323052"}, {"userID": "2527714303", "screen_name": "silvirps", "id": "2527714303"}, {"userID": "142448905", "screen_name": "Stephllewellyn", "id": "142448905"}, {"userID": "1487450708", "screen_name": "lyndseygreen1", "id": "1487450708"}, {"userID": "803704647982653440", "screen_name": "thefluffyfairy", "id": "803704647982653440"}, {"userID": "1565366660", "screen_name": "BuftonR", "id": "1565366660"}, {"userID": "478649895", "screen_name": "kir1975", "id": "478649895"}, {"userID": "185230701", "screen_name": "walk1961", "id": "185230701"}, {"userID": "344320378", "screen_name": "nlclarry1", "id": "344320378"}, {"userID": "290470168", "screen_name": "Catherinicle24", "id": "290470168"}, {"userID": "485993060", "screen_name": "KimVDraper", "id": "485993060"}, {"userID": "1675675494", "screen_name": "christina_ck1", "id": "1675675494"}, {"userID": "835506730511519744", "screen_name": "JackieArcher66", "id": "835506730511519744"}, {"userID": "66873675", "screen_name": "kissmeraas", "id": "66873675"}, {"userID": "866515382", "screen_name": "Becca_lacy", "id": "866515382"}, {"userID": "3332298195", "screen_name": "PinderJoanne", "id": "3332298195"}, {"userID": "4701619707", "screen_name": "davidcavender2", "id": "4701619707"}, {"userID": "3292354622", "screen_name": "t79_rachel", "id": "3292354622"}, {"userID": "796702115712352260", "screen_name": "MoreProsecco", "id": "796702115712352260"}, {"userID": "249589170", "screen_name": "downingarms87", "id": "249589170"}, {"userID": "2229102053", "screen_name": "Cupcakelover_83", "id": "2229102053"}, {"userID": "3394529638", "screen_name": "AbsolutelyAshKy", "id": "3394529638"}, {"userID": "634723977", "screen_name": "julistjohn2", "id": "634723977"}, {"userID": "29725732", "screen_name": "marypopins69900", "id": "29725732"}, {"userID": "820701212777582593", "screen_name": "JusCompetitions", "id": "820701212777582593"}, {"userID": "3001467576", "screen_name": "pgarner37", "id": "3001467576"}, {"userID": "847031536805384193", "screen_name": "PollyL0001", "id": "847031536805384193"}, {"userID": "195721984", "screen_name": "gailspetdelight", "id": "195721984"}, {"userID": "342816915", "screen_name": "KeziaToghill", "id": "342816915"}, {"userID": "20474653", "screen_name": "KaraCariad", "id": "20474653"}, {"userID": "1254440228", "screen_name": "CrystalFez", "id": "1254440228"}, {"userID": "1175216642", "screen_name": "bozavic", "id": "1175216642"}, {"userID": "3222622633", "screen_name": "kimberleyshowes", "id": "3222622633"}, {"userID": "762939556329033728", "screen_name": "OdinMack", "id": "762939556329033728"}, {"userID": "847168810834673666", "screen_name": "Ali23089", "id": "847168810834673666"}, {"userID": "268236371", "screen_name": "LeinadDOP80", "id": "268236371"}, {"userID": "4823771865", "screen_name": "LynnCo77", "id": "4823771865"}, {"userID": "20641021", "screen_name": "awl1984", "id": "20641021"}, {"userID": "56762168", "screen_name": "MrsScrog", "id": "56762168"}, {"userID": "934976106", "screen_name": "laurenceamason", "id": "934976106"}, {"userID": "26598233", "screen_name": "marjoleine72", "id": "26598233"}, {"userID": "3732012507", "screen_name": "jackstrawwk", "id": "3732012507"}, {"userID": "756160171273965568", "screen_name": "katieblair97", "id": "756160171273965568"}, {"userID": "2925894994", "screen_name": "Tinypopple", "id": "2925894994"}, {"userID": "2497503928", "screen_name": "missesLeto44", "id": "2497503928"}, {"userID": "37005779", "screen_name": "Aceso84", "id": "37005779"}, {"userID": "138073766", "screen_name": "manna137", "id": "138073766"}, {"userID": "90840657", "screen_name": "chivas007007", "id": "90840657"}, {"userID": "212295064", "screen_name": "my_shoes93", "id": "212295064"}, {"userID": "591603830", "screen_name": "nataleegosiewsk", "id": "591603830"}, {"userID": "36779225", "screen_name": "WeeMartini", "id": "36779225"}, {"userID": "92717747", "screen_name": "chillijamx", "id": "92717747"}, {"userID": "35908354", "screen_name": "jaizduck", "id": "35908354"}, {"userID": "48704562", "screen_name": "hayleyw1", "id": "48704562"}, {"userID": "226709175", "screen_name": "laurey_xox", "id": "226709175"}, {"userID": "733358001906716673", "screen_name": "sweety03041876", "id": "733358001906716673"}, {"userID": "2291702765", "screen_name": "trayjayh", "id": "2291702765"}, {"userID": "28408397", "screen_name": "jayney84", "id": "28408397"}, {"userID": "89540633", "screen_name": "maci234", "id": "89540633"}, {"userID": "775410000", "screen_name": "zoem1503", "id": "775410000"}, {"userID": "1657900118", "screen_name": "CastleCindie", "id": "1657900118"}, {"userID": "283508965", "screen_name": "BexJ30", "id": "283508965"}, {"userID": "2282700048", "screen_name": "xkatyann88x", "id": "2282700048"}, {"userID": "4250276656", "screen_name": "kristina1020151", "id": "4250276656"}, {"userID": "176437736", "screen_name": "SassyLou31", "id": "176437736"}, {"userID": "1479999518", "screen_name": "alicedixon1993", "id": "1479999518"}, {"userID": "763760766", "screen_name": "xBelinx", "id": "763760766"}, {"userID": "19524060", "screen_name": "jazza1", "id": "19524060"}, {"userID": "220655160", "screen_name": "NuttyNanny1", "id": "220655160"}, {"userID": "3396024802", "screen_name": "Margare42282639", "id": "3396024802"}, {"userID": "2942126015", "screen_name": "s4ss77", "id": "2942126015"}, {"userID": "2544411110", "screen_name": "Peculiar_Lass", "id": "2544411110"}, {"userID": "781625934013161472", "screen_name": "irish_peat", "id": "781625934013161472"}, {"userID": "1935475783", "screen_name": "fluffybelly1966", "id": "1935475783"}, {"userID": "2613875930", "screen_name": "nicholaire", "id": "2613875930"}, {"userID": "45013334", "screen_name": "nattylara", "id": "45013334"}, {"userID": "1882744730", "screen_name": "tyrabobo", "id": "1882744730"}, {"userID": "467848575", "screen_name": "GemmaTempest", "id": "467848575"}, {"userID": "299292394", "screen_name": "jem289", "id": "299292394"}, {"userID": "2587040573", "screen_name": "HazelburkeHazel", "id": "2587040573"}, {"userID": "529514235", "screen_name": "AmeliaGrinyer", "id": "529514235"}, {"userID": "833384982", "screen_name": "gibbonsroland1", "id": "833384982"}, {"userID": "806842466477502465", "screen_name": "Loopyb31", "id": "806842466477502465"}, {"userID": "1380625604", "screen_name": "wannawincompo", "id": "1380625604"}, {"userID": "287349925", "screen_name": "charliesantix", "id": "287349925"}, {"userID": "1384362163", "screen_name": "SammyEdwards65", "id": "1384362163"}, {"userID": "274076415", "screen_name": "PostieChrissy", "id": "274076415"}, {"userID": "2911536226", "screen_name": "Dunnster81", "id": "2911536226"}, {"userID": "73552370", "screen_name": "donk48", "id": "73552370"}, {"userID": "725434703449341953", "screen_name": "AngelaSquiresa", "id": "725434703449341953"}, {"userID": "209951303", "screen_name": "silvernemesis", "id": "209951303"}, {"userID": "1130700288", "screen_name": "Lainley20", "id": "1130700288"}, {"userID": "2285022086", "screen_name": "natalie_gibbing", "id": "2285022086"}, {"userID": "707638180644786176", "screen_name": "AlfieDaley1", "id": "707638180644786176"}, {"userID": "22180423", "screen_name": "sheridarby", "id": "22180423"}, {"userID": "3178610559", "screen_name": "cbrill1996", "id": "3178610559"}, {"userID": "809161191297863680", "screen_name": "xxx_ARIANA_xxx_", "id": "809161191297863680"}, {"userID": "817819113854746624", "screen_name": "tedder_mrs", "id": "817819113854746624"}, {"userID": "3343011467", "screen_name": "m_bella77", "id": "3343011467"}, {"userID": "455154619", "screen_name": "katpol80", "id": "455154619"}, {"userID": "1970379884", "screen_name": "Azashie", "id": "1970379884"}, {"userID": "804462440469712900", "screen_name": "Nattaylor777", "id": "804462440469712900"}, {"userID": "2235615924", "screen_name": "uksalsald", "id": "2235615924"}, {"userID": "623959558", "screen_name": "KatyCJohnston", "id": "623959558"}, {"userID": "4515145576", "screen_name": "jaimelovesbooks", "id": "4515145576"}, {"userID": "2459834251", "screen_name": "p1pkins", "id": "2459834251"}, {"userID": "597697138", "screen_name": "angelasurgenor1", "id": "597697138"}, {"userID": "787965691936772096", "screen_name": "gettogirl16", "id": "787965691936772096"}, {"userID": "28874932", "screen_name": "lilmiss80", "id": "28874932"}, {"userID": "3352215479", "screen_name": "Jun_Sal92", "id": "3352215479"}, {"userID": "340835453", "screen_name": "marblesmissing1", "id": "340835453"}, {"userID": "44322318", "screen_name": "JohnnyGlen", "id": "44322318"}, {"userID": "311608797", "screen_name": "jhatch30", "id": "311608797"}, {"userID": "168611225", "screen_name": "andy_wedge", "id": "168611225"}, {"userID": "833416514862776324", "screen_name": "Chloe_11_08", "id": "833416514862776324"}, {"userID": "119019427", "screen_name": "bhaskieboo", "id": "119019427"}, {"userID": "27061584", "screen_name": "CheekyKyson", "id": "27061584"}, {"userID": "506292269", "screen_name": "SheWolfMemoirs", "id": "506292269"}, {"userID": "147909116", "screen_name": "teetee63", "id": "147909116"}, {"userID": "163607977", "screen_name": "laylafletcher", "id": "163607977"}, {"userID": "42082083", "screen_name": "JoGodfray", "id": "42082083"}, {"userID": "1377846518", "screen_name": "cvh86", "id": "1377846518"}, {"userID": "61938475", "screen_name": "kitaaa93", "id": "61938475"}, {"userID": "298104246", "screen_name": "Paul_Chambers60", "id": "298104246"}, {"userID": "116451098", "screen_name": "greigo_uk", "id": "116451098"}, {"userID": "831211246842163200", "screen_name": "Kenlowe43095658", "id": "831211246842163200"}, {"userID": "738081314281271296", "screen_name": "JoanneMcKenna13", "id": "738081314281271296"}, {"userID": "198065433", "screen_name": "Zoeeyy00", "id": "198065433"}, {"userID": "500382943", "screen_name": "janejett123", "id": "500382943"}, {"userID": "4321698555", "screen_name": "georgetheminer", "id": "4321698555"}, {"userID": "68712302", "screen_name": "beachrambler", "id": "68712302"}, {"userID": "716707262564270081", "screen_name": "Kieran__Victor", "id": "716707262564270081"}, {"userID": "40522823", "screen_name": "lstewarts", "id": "40522823"}, {"userID": "765294501816594432", "screen_name": "tashandalex1993", "id": "765294501816594432"}, {"userID": "376333378", "screen_name": "1kevbanham", "id": "376333378"}, {"userID": "829968773591478272", "screen_name": "MocktailMum", "id": "829968773591478272"}, {"userID": "45019930", "screen_name": "lucyirv", "id": "45019930"}, {"userID": "313895145", "screen_name": "rayary31", "id": "313895145"}, {"userID": "58864538", "screen_name": "salvagebrav", "id": "58864538"}, {"userID": "51490108", "screen_name": "FunKhoosE", "id": "51490108"}, {"userID": "4824686326", "screen_name": "kirksinspace", "id": "4824686326"}, {"userID": "782139120533532672", "screen_name": "PadtoughMega", "id": "782139120533532672"}, {"userID": "2953025733", "screen_name": "janj2301", "id": "2953025733"}, {"userID": "33332180", "screen_name": "beedle82", "id": "33332180"}, {"userID": "1301573707", "screen_name": "thegeekmiles", "id": "1301573707"}, {"userID": "531298761", "screen_name": "gavin_priestley", "id": "531298761"}, {"userID": "947401314", "screen_name": "karenwalder1", "id": "947401314"}, {"userID": "736259997873639424", "screen_name": "KatieselaeS", "id": "736259997873639424"}, {"userID": "470088458", "screen_name": "LiamS79", "id": "470088458"}, {"userID": "442035699", "screen_name": "LauraIreland023", "id": "442035699"}, {"userID": "564500810", "screen_name": "KateOwen17", "id": "564500810"}, {"userID": "4909541584", "screen_name": "Nicolah37976523", "id": "4909541584"}, {"userID": "2921645363", "screen_name": "benrobb007", "id": "2921645363"}, {"userID": "803729669136744449", "screen_name": "ChloeBusby4", "id": "803729669136744449"}, {"userID": "47180329", "screen_name": "jacja", "id": "47180329"}, {"userID": "845771208129990657", "screen_name": "SK10483", "id": "845771208129990657"}, {"userID": "1280219184", "screen_name": "hayleycolburn84", "id": "1280219184"}, {"userID": "18553607", "screen_name": "Smhumm", "id": "18553607"}, {"userID": "731403495329398784", "screen_name": "20timesYSB", "id": "731403495329398784"}, {"userID": "4663265657", "screen_name": "Paulacomp0101", "id": "4663265657"}, {"userID": "755713991763173376", "screen_name": "Laurenxx0xx0", "id": "755713991763173376"}, {"userID": "559380601", "screen_name": "JanetRockwell80", "id": "559380601"}, {"userID": "246852909", "screen_name": "jujugaboo", "id": "246852909"}, {"userID": "2417887261", "screen_name": "Designingnu", "id": "2417887261"}, {"userID": "2156592433", "screen_name": "fullarton121", "id": "2156592433"}, {"userID": "354703832", "screen_name": "piggypops123", "id": "354703832"}, {"userID": "82333550", "screen_name": "KnooKie_uK", "id": "82333550"}, {"userID": "750066315088584704", "screen_name": "DanHamill1987", "id": "750066315088584704"}, {"userID": "847002060105109504", "screen_name": "Angela_X0X0X0", "id": "847002060105109504"}, {"userID": "597712346", "screen_name": "sarahrees151286", "id": "597712346"}, {"userID": "28819839", "screen_name": "LindaM1955", "id": "28819839"}, {"userID": "1314297114", "screen_name": "RosieOddy58", "id": "1314297114"}, {"userID": "21644891", "screen_name": "Colb1811", "id": "21644891"}, {"userID": "230198134", "screen_name": "cadizzye", "id": "230198134"}, {"userID": "20071095", "screen_name": "lisanorfolk", "id": "20071095"}, {"userID": "114538347", "screen_name": "smnrose", "id": "114538347"}, {"userID": "2320854000", "screen_name": "xmaskraken", "id": "2320854000"}, {"userID": "823999602", "screen_name": "clairewoods32", "id": "823999602"}, {"userID": "20234513", "screen_name": "relisys222", "id": "20234513"}, {"userID": "76941657", "screen_name": "Josiewollerton", "id": "76941657"}, {"userID": "3035075865", "screen_name": "lozzlelozz", "id": "3035075865"}, {"userID": "19031887", "screen_name": "Madein1961", "id": "19031887"}, {"userID": "142358555", "screen_name": "lydfp_bobbysmum", "id": "142358555"}, {"userID": "1393056800", "screen_name": "landonsmum", "id": "1393056800"}, {"userID": "20154261", "screen_name": "rachiedoos", "id": "20154261"}, {"userID": "2155131240", "screen_name": "IsabellaE2807", "id": "2155131240"}, {"userID": "435940448", "screen_name": "sequin_star", "id": "435940448"}, {"userID": "374986265", "screen_name": "vickyeaston1234", "id": "374986265"}, {"userID": "371848421", "screen_name": "sarahjanecarter", "id": "371848421"}, {"userID": "813588096", "screen_name": "Aftershock088", "id": "813588096"}, {"userID": "327317638", "screen_name": "jane1346", "id": "327317638"}, {"userID": "850983715", "screen_name": "mimkakrutska", "id": "850983715"}, {"userID": "1133691006", "screen_name": "mattstuttle88", "id": "1133691006"}, {"userID": "341031362", "screen_name": "bridie4", "id": "341031362"}, {"userID": "1538137638", "screen_name": "jbsguapa", "id": "1538137638"}, {"userID": "421139897", "screen_name": "Rtlikewin", "id": "421139897"}, {"userID": "3346089730", "screen_name": "jemjemdwyer", "id": "3346089730"}, {"userID": "87147968", "screen_name": "JuJu_Carbo", "id": "87147968"}, {"userID": "65168107", "screen_name": "ClareJFox", "id": "65168107"}, {"userID": "62562052", "screen_name": "WendyJeanJones", "id": "62562052"}, {"userID": "2292987499", "screen_name": "AnnabelGreaves", "id": "2292987499"}, {"userID": "2565381066", "screen_name": "christinaearl3", "id": "2565381066"}, {"userID": "750233401492402176", "screen_name": "Dive_Safe", "id": "750233401492402176"}, {"userID": "4374702615", "screen_name": "collette_mackey", "id": "4374702615"}, {"userID": "18608566", "screen_name": "samsambyrne", "id": "18608566"}, {"userID": "2639861583", "screen_name": "lionbar2012", "id": "2639861583"}], "links": [{"source": 0, "target": 296}, {"source": 1, "target": 224}, {"source": 1, "target": 32}, {"source": 1, "target": 17}, {"source": 2, "target": 211}, {"source": 2, "target": 130}, {"source": 2, "target": 154}, {"source": 2, "target": 50}, {"source": 2, "target": 224}, {"source": 2, "target": 145}, {"source": 2, "target": 16}, {"source": 2, "target": 56}, {"source": 3, "target": 217}, {"source": 3, "target": 169}, {"source": 3, "target": 297}, {"source": 3, "target": 207}, {"source": 4, "target": 214}, {"source": 4, "target": 302}, {"source": 4, "target": 196}, {"source": 5, "target": 32}, {"source": 5, "target": 253}, {"source": 5, "target": 207}, {"source": 5, "target": 150}, {"source": 6, "target": 224}, {"source": 6, "target": 53}, {"source": 6, "target": 222}, {"source": 7, "target": 224}, {"source": 10, "target": 143}, {"source": 10, "target": 168}, {"source": 10, "target": 82}, {"source": 10, "target": 114}, {"source": 10, "target": 216}, {"source": 10, "target": 279}, {"source": 10, "target": 197}, {"source": 10, "target": 179}, {"source": 10, "target": 224}, {"source": 10, "target": 253}, {"source": 10, "target": 16}, {"source": 11, "target": 301}, {"source": 11, "target": 36}, {"source": 11, "target": 221}, {"source": 12, "target": 73}, {"source": 12, "target": 112}, {"source": 12, "target": 213}, {"source": 13, "target": 224}, {"source": 13, "target": 53}, {"source": 13, "target": 121}, {"source": 13, "target": 207}, {"source": 16, "target": 53}, {"source": 17, "target": 32}, {"source": 17, "target": 253}, {"source": 17, "target": 53}, {"source": 17, "target": 192}, {"source": 17, "target": 77}, {"source": 17, "target": 96}, {"source": 17, "target": 123}, {"source": 17, "target": 279}, {"source": 17, "target": 102}, {"source": 17, "target": 50}, {"source": 17, "target": 278}, {"source": 17, "target": 125}, {"source": 17, "target": 216}, {"source": 17, "target": 224}, {"source": 17, "target": 124}, {"source": 17, "target": 226}, {"source": 17, "target": 296}, {"source": 17, "target": 136}, {"source": 17, "target": 207}, {"source": 18, "target": 66}, {"source": 18, "target": 97}, {"source": 18, "target": 201}, {"source": 19, "target": 213}, {"source": 20, "target": 38}, {"source": 20, "target": 270}, {"source": 20, "target": 196}, {"source": 20, "target": 297}, {"source": 20, "target": 132}, {"source": 20, "target": 153}, {"source": 20, "target": 114}, {"source": 20, "target": 176}, {"source": 20, "target": 296}, {"source": 20, "target": 282}, {"source": 20, "target": 262}, {"source": 20, "target": 145}, {"source": 20, "target": 206}, {"source": 21, "target": 239}, {"source": 21, "target": 53}, {"source": 21, "target": 150}, {"source": 21, "target": 213}, {"source": 22, "target": 224}, {"source": 22, "target": 53}, {"source": 24, "target": 224}, {"source": 24, "target": 53}, {"source": 24, "target": 38}, {"source": 24, "target": 296}, {"source": 25, "target": 259}, {"source": 25, "target": 224}, {"source": 26, "target": 115}, {"source": 27, "target": 232}, {"source": 27, "target": 234}, {"source": 27, "target": 152}, {"source": 27, "target": 77}, {"source": 27, "target": 238}, {"source": 27, "target": 230}, {"source": 27, "target": 167}, {"source": 27, "target": 150}, {"source": 27, "target": 153}, {"source": 27, "target": 184}, {"source": 27, "target": 188}, {"source": 27, "target": 243}, {"source": 27, "target": 274}, {"source": 27, "target": 279}, {"source": 27, "target": 281}, {"source": 27, "target": 53}, {"source": 27, "target": 56}, {"source": 27, "target": 207}, {"source": 27, "target": 131}, {"source": 27, "target": 60}, {"source": 27, "target": 67}, {"source": 27, "target": 263}, {"source": 27, "target": 224}, {"source": 27, "target": 293}, {"source": 28, "target": 301}, {"source": 28, "target": 203}, {"source": 28, "target": 53}, {"source": 28, "target": 32}, {"source": 29, "target": 224}, {"source": 29, "target": 53}, {"source": 29, "target": 150}, {"source": 31, "target": 224}, {"source": 31, "target": 53}, {"source": 31, "target": 192}, {"source": 32, "target": 203}, {"source": 32, "target": 281}, {"source": 32, "target": 52}, {"source": 32, "target": 66}, {"source": 32, "target": 155}, {"source": 32, "target": 253}, {"source": 32, "target": 153}, {"source": 32, "target": 81}, {"source": 32, "target": 49}, {"source": 32, "target": 224}, {"source": 32, "target": 123}, {"source": 32, "target": 67}, {"source": 32, "target": 207}, {"source": 33, "target": 210}, {"source": 33, "target": 153}, {"source": 33, "target": 56}, {"source": 33, "target": 224}, {"source": 33, "target": 53}, {"source": 33, "target": 140}, {"source": 34, "target": 66}, {"source": 34, "target": 103}, {"source": 35, "target": 53}, {"source": 35, "target": 98}, {"source": 36, "target": 53}, {"source": 36, "target": 175}, {"source": 36, "target": 295}, {"source": 36, "target": 282}, {"source": 37, "target": 77}, {"source": 37, "target": 224}, {"source": 37, "target": 96}, {"source": 37, "target": 150}, {"source": 38, "target": 231}, {"source": 38, "target": 267}, {"source": 38, "target": 77}, {"source": 38, "target": 162}, {"source": 38, "target": 53}, {"source": 38, "target": 207}, {"source": 39, "target": 150}, {"source": 39, "target": 278}, {"source": 39, "target": 86}, {"source": 39, "target": 293}, {"source": 39, "target": 136}, {"source": 39, "target": 207}, {"source": 41, "target": 224}, {"source": 41, "target": 53}, {"source": 42, "target": 143}, {"source": 44, "target": 224}, {"source": 44, "target": 201}, {"source": 44, "target": 117}, {"source": 45, "target": 224}, {"source": 45, "target": 53}, {"source": 45, "target": 227}, {"source": 47, "target": 224}, {"source": 47, "target": 171}, {"source": 47, "target": 53}, {"source": 47, "target": 217}, {"source": 47, "target": 143}, {"source": 48, "target": 224}, {"source": 48, "target": 281}, {"source": 48, "target": 53}, {"source": 49, "target": 77}, {"source": 49, "target": 224}, {"source": 49, "target": 121}, {"source": 49, "target": 150}, {"source": 50, "target": 150}, {"source": 50, "target": 132}, {"source": 50, "target": 224}, {"source": 50, "target": 53}, {"source": 51, "target": 224}, {"source": 51, "target": 53}, {"source": 51, "target": 150}, {"source": 53, "target": 181}, {"source": 53, "target": 95}, {"source": 53, "target": 279}, {"source": 53, "target": 56}, {"source": 53, "target": 94}, {"source": 53, "target": 64}, {"source": 53, "target": 70}, {"source": 53, "target": 74}, {"source": 53, "target": 77}, {"source": 53, "target": 80}, {"source": 53, "target": 230}, {"source": 53, "target": 150}, {"source": 53, "target": 96}, {"source": 53, "target": 97}, {"source": 53, "target": 99}, {"source": 53, "target": 103}, {"source": 53, "target": 105}, {"source": 53, "target": 65}, {"source": 53, "target": 76}, {"source": 53, "target": 117}, {"source": 53, "target": 123}, {"source": 53, "target": 127}, {"source": 53, "target": 132}, {"source": 53, "target": 304}, {"source": 53, "target": 134}, {"source": 53, "target": 248}, {"source": 53, "target": 263}, {"source": 53, "target": 145}, {"source": 53, "target": 293}, {"source": 53, "target": 147}, {"source": 53, "target": 149}, {"source": 53, "target": 153}, {"source": 53, "target": 100}, {"source": 53, "target": 165}, {"source": 53, "target": 168}, {"source": 53, "target": 84}, {"source": 53, "target": 162}, {"source": 53, "target": 175}, {"source": 53, "target": 171}, {"source": 53, "target": 180}, {"source": 53, "target": 182}, {"source": 53, "target": 183}, {"source": 53, "target": 122}, {"source": 53, "target": 188}, {"source": 53, "target": 269}, {"source": 53, "target": 274}, {"source": 53, "target": 199}, {"source": 53, "target": 202}, {"source": 53, "target": 210}, {"source": 53, "target": 213}, {"source": 53, "target": 66}, {"source": 53, "target": 216}, {"source": 53, "target": 218}, {"source": 53, "target": 221}, {"source": 53, "target": 224}, {"source": 53, "target": 227}, {"source": 53, "target": 192}, {"source": 53, "target": 231}, {"source": 53, "target": 232}, {"source": 53, "target": 233}, {"source": 53, "target": 234}, {"source": 53, "target": 236}, {"source": 53, "target": 238}, {"source": 53, "target": 291}, {"source": 53, "target": 251}, {"source": 53, "target": 256}, {"source": 53, "target": 261}, {"source": 53, "target": 262}, {"source": 53, "target": 139}, {"source": 53, "target": 55}, {"source": 53, "target": 163}, {"source": 53, "target": 267}, {"source": 53, "target": 195}, {"source": 53, "target": 278}, {"source": 53, "target": 282}, {"source": 53, "target": 161}, {"source": 53, "target": 286}, {"source": 53, "target": 287}, {"source": 53, "target": 146}, {"source": 53, "target": 294}, {"source": 53, "target": 296}, {"source": 53, "target": 300}, {"source": 54, "target": 224}, {"source": 55, "target": 188}, {"source": 55, "target": 105}, {"source": 55, "target": 207}, {"source": 56, "target": 128}, {"source": 56, "target": 143}, {"source": 56, "target": 152}, {"source": 56, "target": 213}, {"source": 56, "target": 188}, {"source": 56, "target": 224}, {"source": 56, "target": 65}, {"source": 56, "target": 207}, {"source": 57, "target": 224}, {"source": 57, "target": 183}, {"source": 58, "target": 224}, {"source": 58, "target": 132}, {"source": 59, "target": 188}, {"source": 59, "target": 124}, {"source": 60, "target": 121}, {"source": 60, "target": 258}, {"source": 64, "target": 224}, {"source": 64, "target": 150}, {"source": 65, "target": 224}, {"source": 65, "target": 278}, {"source": 65, "target": 218}, {"source": 66, "target": 77}, {"source": 66, "target": 195}, {"source": 66, "target": 183}, {"source": 66, "target": 293}, {"source": 67, "target": 121}, {"source": 68, "target": 224}, {"source": 71, "target": 207}, {"source": 72, "target": 281}, {"source": 73, "target": 112}, {"source": 73, "target": 213}, {"source": 74, "target": 224}, {"source": 74, "target": 145}, {"source": 74, "target": 270}, {"source": 75, "target": 224}, {"source": 75, "target": 282}, {"source": 76, "target": 224}, {"source": 76, "target": 222}, {"source": 77, "target": 188}, {"source": 77, "target": 288}, {"source": 77, "target": 268}, {"source": 77, "target": 236}, {"source": 77, "target": 153}, {"source": 77, "target": 162}, {"source": 77, "target": 134}, {"source": 77, "target": 296}, {"source": 77, "target": 221}, {"source": 77, "target": 206}, {"source": 77, "target": 224}, {"source": 77, "target": 267}, {"source": 77, "target": 207}, {"source": 78, "target": 224}, {"source": 80, "target": 91}, {"source": 80, "target": 150}, {"source": 80, "target": 207}, {"source": 82, "target": 224}, {"source": 82, "target": 207}, {"source": 82, "target": 276}, {"source": 82, "target": 150}, {"source": 83, "target": 224}, {"source": 83, "target": 190}, {"source": 84, "target": 224}, {"source": 85, "target": 130}, {"source": 85, "target": 242}, {"source": 85, "target": 121}, {"source": 85, "target": 198}, {"source": 85, "target": 171}, {"source": 85, "target": 224}, {"source": 85, "target": 87}, {"source": 85, "target": 303}, {"source": 85, "target": 173}, {"source": 85, "target": 165}, {"source": 85, "target": 207}, {"source": 86, "target": 222}, {"source": 86, "target": 150}, {"source": 86, "target": 293}, {"source": 86, "target": 136}, {"source": 89, "target": 152}, {"source": 89, "target": 115}, {"source": 89, "target": 132}, {"source": 89, "target": 213}, {"source": 89, "target": 221}, {"source": 89, "target": 204}, {"source": 90, "target": 213}, {"source": 91, "target": 224}, {"source": 91, "target": 140}, {"source": 91, "target": 241}, {"source": 94, "target": 224}, {"source": 95, "target": 224}, {"source": 96, "target": 188}, {"source": 96, "target": 213}, {"source": 96, "target": 153}, {"source": 96, "target": 150}, {"source": 96, "target": 296}, {"source": 96, "target": 123}, {"source": 96, "target": 207}, {"source": 97, "target": 224}, {"source": 97, "target": 120}, {"source": 97, "target": 150}, {"source": 99, "target": 224}, {"source": 100, "target": 224}, {"source": 100, "target": 222}, {"source": 102, "target": 206}, {"source": 102, "target": 150}, {"source": 103, "target": 224}, {"source": 104, "target": 188}, {"source": 105, "target": 297}, {"source": 105, "target": 213}, {"source": 105, "target": 130}, {"source": 105, "target": 296}, {"source": 105, "target": 183}, {"source": 105, "target": 207}, {"source": 106, "target": 224}, {"source": 107, "target": 224}, {"source": 107, "target": 253}, {"source": 107, "target": 150}, {"source": 108, "target": 188}, {"source": 112, "target": 213}, {"source": 114, "target": 224}, {"source": 114, "target": 160}, {"source": 114, "target": 150}, {"source": 115, "target": 297}, {"source": 115, "target": 150}, {"source": 115, "target": 171}, {"source": 115, "target": 221}, {"source": 115, "target": 183}, {"source": 115, "target": 224}, {"source": 115, "target": 293}, {"source": 116, "target": 224}, {"source": 117, "target": 224}, {"source": 118, "target": 166}, {"source": 119, "target": 198}, {"source": 119, "target": 173}, {"source": 120, "target": 268}, {"source": 120, "target": 217}, {"source": 120, "target": 257}, {"source": 120, "target": 224}, {"source": 120, "target": 206}, {"source": 121, "target": 196}, {"source": 121, "target": 153}, {"source": 121, "target": 155}, {"source": 121, "target": 208}, {"source": 121, "target": 162}, {"source": 121, "target": 175}, {"source": 121, "target": 259}, {"source": 121, "target": 267}, {"source": 121, "target": 268}, {"source": 121, "target": 243}, {"source": 121, "target": 130}, {"source": 121, "target": 279}, {"source": 121, "target": 282}, {"source": 121, "target": 173}, {"source": 121, "target": 206}, {"source": 121, "target": 209}, {"source": 121, "target": 134}, {"source": 121, "target": 216}, {"source": 121, "target": 296}, {"source": 121, "target": 154}, {"source": 121, "target": 303}, {"source": 121, "target": 228}, {"source": 122, "target": 224}, {"source": 122, "target": 222}, {"source": 123, "target": 253}, {"source": 123, "target": 224}, {"source": 123, "target": 207}, {"source": 125, "target": 224}, {"source": 125, "target": 281}, {"source": 125, "target": 256}, {"source": 125, "target": 150}, {"source": 127, "target": 224}, {"source": 130, "target": 188}, {"source": 130, "target": 136}, {"source": 130, "target": 207}, {"source": 131, "target": 224}, {"source": 132, "target": 279}, {"source": 132, "target": 160}, {"source": 132, "target": 228}, {"source": 132, "target": 293}, {"source": 132, "target": 258}, {"source": 132, "target": 207}, {"source": 134, "target": 143}, {"source": 134, "target": 268}, {"source": 134, "target": 206}, {"source": 135, "target": 224}, {"source": 135, "target": 199}, {"source": 135, "target": 150}, {"source": 136, "target": 188}, {"source": 136, "target": 278}, {"source": 139, "target": 213}, {"source": 140, "target": 188}, {"source": 140, "target": 207}, {"source": 140, "target": 197}, {"source": 143, "target": 188}, {"source": 143, "target": 268}, {"source": 143, "target": 279}, {"source": 143, "target": 221}, {"source": 143, "target": 206}, {"source": 143, "target": 291}, {"source": 143, "target": 207}, {"source": 143, "target": 223}, {"source": 144, "target": 224}, {"source": 144, "target": 253}, {"source": 145, "target": 230}, {"source": 145, "target": 224}, {"source": 145, "target": 207}, {"source": 146, "target": 262}, {"source": 147, "target": 224}, {"source": 147, "target": 227}, {"source": 147, "target": 278}, {"source": 149, "target": 224}, {"source": 150, "target": 175}, {"source": 150, "target": 151}, {"source": 150, "target": 238}, {"source": 150, "target": 216}, {"source": 150, "target": 157}, {"source": 150, "target": 178}, {"source": 150, "target": 263}, {"source": 150, "target": 188}, {"source": 150, "target": 274}, {"source": 150, "target": 276}, {"source": 150, "target": 277}, {"source": 150, "target": 278}, {"source": 150, "target": 198}, {"source": 150, "target": 281}, {"source": 150, "target": 204}, {"source": 150, "target": 173}, {"source": 150, "target": 296}, {"source": 150, "target": 224}, {"source": 150, "target": 221}, {"source": 150, "target": 282}, {"source": 151, "target": 224}, {"source": 152, "target": 224}, {"source": 153, "target": 188}, {"source": 153, "target": 276}, {"source": 153, "target": 176}, {"source": 153, "target": 262}, {"source": 153, "target": 293}, {"source": 153, "target": 207}, {"source": 154, "target": 186}, {"source": 155, "target": 296}, {"source": 155, "target": 171}, {"source": 155, "target": 217}, {"source": 155, "target": 201}, {"source": 155, "target": 206}, {"source": 158, "target": 224}, {"source": 161, "target": 224}, {"source": 162, "target": 231}, {"source": 162, "target": 175}, {"source": 162, "target": 274}, {"source": 162, "target": 224}, {"source": 162, "target": 207}, {"source": 163, "target": 224}, {"source": 164, "target": 186}, {"source": 165, "target": 224}, {"source": 166, "target": 257}, {"source": 168, "target": 224}, {"source": 169, "target": 224}, {"source": 169, "target": 270}, {"source": 171, "target": 263}, {"source": 171, "target": 274}, {"source": 171, "target": 279}, {"source": 171, "target": 281}, {"source": 171, "target": 175}, {"source": 172, "target": 213}, {"source": 173, "target": 224}, {"source": 173, "target": 207}, {"source": 175, "target": 222}, {"source": 175, "target": 224}, {"source": 175, "target": 207}, {"source": 178, "target": 224}, {"source": 178, "target": 183}, {"source": 180, "target": 219}, {"source": 181, "target": 224}, {"source": 182, "target": 224}, {"source": 183, "target": 278}, {"source": 183, "target": 221}, {"source": 184, "target": 224}, {"source": 187, "target": 224}, {"source": 188, "target": 230}, {"source": 188, "target": 259}, {"source": 188, "target": 265}, {"source": 188, "target": 243}, {"source": 188, "target": 191}, {"source": 188, "target": 284}, {"source": 188, "target": 295}, {"source": 188, "target": 224}, {"source": 193, "target": 224}, {"source": 194, "target": 224}, {"source": 196, "target": 206}, {"source": 196, "target": 207}, {"source": 198, "target": 216}, {"source": 202, "target": 224}, {"source": 202, "target": 253}, {"source": 203, "target": 224}, {"source": 204, "target": 263}, {"source": 205, "target": 224}, {"source": 206, "target": 268}, {"source": 206, "target": 234}, {"source": 206, "target": 276}, {"source": 206, "target": 247}, {"source": 206, "target": 207}, {"source": 207, "target": 243}, {"source": 207, "target": 230}, {"source": 207, "target": 256}, {"source": 207, "target": 262}, {"source": 207, "target": 267}, {"source": 207, "target": 268}, {"source": 207, "target": 278}, {"source": 207, "target": 281}, {"source": 207, "target": 296}, {"source": 207, "target": 298}, {"source": 207, "target": 224}, {"source": 208, "target": 224}, {"source": 208, "target": 213}, {"source": 209, "target": 257}, {"source": 209, "target": 297}, {"source": 210, "target": 274}, {"source": 210, "target": 289}, {"source": 211, "target": 224}, {"source": 212, "target": 224}, {"source": 213, "target": 267}, {"source": 213, "target": 279}, {"source": 213, "target": 224}, {"source": 214, "target": 302}, {"source": 215, "target": 224}, {"source": 215, "target": 278}, {"source": 215, "target": 287}, {"source": 216, "target": 296}, {"source": 216, "target": 278}, {"source": 217, "target": 279}, {"source": 218, "target": 224}, {"source": 218, "target": 299}, {"source": 218, "target": 296}, {"source": 219, "target": 224}, {"source": 220, "target": 224}, {"source": 221, "target": 222}, {"source": 221, "target": 256}, {"source": 222, "target": 288}, {"source": 222, "target": 274}, {"source": 222, "target": 296}, {"source": 222, "target": 224}, {"source": 223, "target": 224}, {"source": 223, "target": 270}, {"source": 223, "target": 286}, {"source": 224, "target": 226}, {"source": 224, "target": 243}, {"source": 224, "target": 279}, {"source": 224, "target": 293}, {"source": 224, "target": 284}, {"source": 224, "target": 247}, {"source": 224, "target": 269}, {"source": 224, "target": 274}, {"source": 224, "target": 232}, {"source": 224, "target": 236}, {"source": 224, "target": 238}, {"source": 224, "target": 242}, {"source": 224, "target": 248}, {"source": 224, "target": 258}, {"source": 224, "target": 251}, {"source": 224, "target": 256}, {"source": 224, "target": 262}, {"source": 224, "target": 264}, {"source": 224, "target": 277}, {"source": 224, "target": 281}, {"source": 224, "target": 282}, {"source": 224, "target": 285}, {"source": 224, "target": 287}, {"source": 224, "target": 233}, {"source": 224, "target": 295}, {"source": 224, "target": 296}, {"source": 224, "target": 300}, {"source": 224, "target": 303}, {"source": 224, "target": 294}, {"source": 225, "target": 278}, {"source": 227, "target": 296}, {"source": 227, "target": 258}, {"source": 227, "target": 287}, {"source": 230, "target": 297}, {"source": 232, "target": 301}, {"source": 232, "target": 233}, {"source": 236, "target": 279}, {"source": 236, "target": 254}, {"source": 236, "target": 302}, {"source": 236, "target": 305}, {"source": 241, "target": 247}, {"source": 243, "target": 278}, {"source": 253, "target": 269}, {"source": 253, "target": 296}, {"source": 254, "target": 305}, {"source": 259, "target": 278}, {"source": 262, "target": 289}, {"source": 263, "target": 279}, {"source": 278, "target": 297}, {"source": 278, "target": 296}, {"source": 279, "target": 296}, {"source": 281, "target": 296}, {"source": 282, "target": 298}, {"source": 295, "target": 298}, {"source": 296, "target": 303}], "multigraph": false}